edu_core_lib
