Metadata-Version: 1.1
Name: edu-core-lib
Version: 0.3.5
Summary: UNKNOWN
Home-page: https://github.com/BlipIQSciences/edu-core-lib
Author: Rohit Kumar
Author-email: rohit@blipiq.com
License: MIT
Keywords: edu-library
Platform: UNKNOWN
Classifier: Development Status :: 3 - Alpha
Classifier: License :: OSI Approved :: MIT License
Classifier: Programming Language :: Python :: 3.8
Classifier: Topic :: Software Development :: Libraries :: Python Modules
